Workbook

Sheet trial
B1: Diamond Star Arabia Industrial Company(Namma)
B2: Trial Balance 01-01-2026 To 31-05-2026
B5: Code | C5: Account | D5: Opening Balance | E5: Debits | F5: Credits | G5: Net Change | H5: Closing Balance | I5: Sub Group
B6: FCA | C6: CONTROL A/Cs
B7: JEC-001 | C7: Journal Entries Control A/C | D7: 0 | E7: 22179370 | F7: 22179370 | G7: =E7-F7 -> 0 | H7: =D7+G7 -> 0
B8: 10 | C8: Cash & Cash Equivallants | G8: =E8-F8 -> 0 | H8: =D8+G8 -> 0
B9: 100 | C9: Petty Cash | G9: =E9-F9 -> 0 | H9: =D9+G9 -> 0
B10: 0100-01 | C10: Petty Cash-Accounts | D10: 0 | E10: 2036922.5 | F10: 2015179.5 | G10: =E10-F10 -> 21743.04 | H10: =D10+G10 -> 21743.04 | I10: Bank balances and cash
B11: 0100-02 | C11: Petty Cash-Expenses | D11: 0 | E11: 123287.42 | F11: 123287.42 | G11: =E11-F11 -> 0 | H11: =D11+G11 -> 0 | I11: Bank balances and cash
B12: 0100-03 | C12: Petty Cash - Material | D12: 0 | E12: 1891895.6 | F12: 1891895.6 | G12: =E12-F12 -> 0 | H12: =D12+G12 -> 0 | I12: Bank balances and cash
B13: 0100-08 | C13: Cash In Hand-2024 | D13: 0 | E13: 405334 | F13: 405334 | G13: =E13-F13 -> 0 | H13: =D13+G13 -> 0 | I13: Bank balances and cash
B14: 102 | C14: Bank | G14: =E14-F14 -> 0 | H14: =D14+G14 -> 0 | I14: Bank balances and cash
B15: 0102-03 | C15: Riyad Bank IBAN- SA3120000001364256539940 | D15: 0 | E15: 6842.5 | F15: 6842.5 | G15: =E15-F15 -> 0 | H15: =D15+G15 -> 0 | I15: Bank balances and cash
B16: 0102-09 | C16: Riyad Bank-136425689994 (DSA) | D16: 0 | E16: 8919704.8 | F16: 8887800.3 | G16: =E16-F16 -> 31904.55 | H16: =D16+G16 -> 31904.55 | I16: Bank balances and cash
B17: 0102-10 | C17: AL RAJHI BANK-45300-001-0006080453175 | D17: 0 | E17: 100 | F17: 0 | G17: =E17-F17 -> 100 | H17: =D17+G17 -> 100 | I17: Bank balances and cash
B18: 101 | C18: Cash In Collection | G18: =E18-F18 -> 0 | H18: =D18+G18 -> 0 | I18: Bank balances and cash
B19: 0101-01 | C19: Cash In Collection | D19: 0 | E19: 2279166.5 | F19: 2279166.5 | G19: =E19-F19 -> 0 | H19: =D19+G19 -> 0 | I19: Bank balances and cash
B20: 400 | C20: Accounts Receivables | G20: =E20-F20 -> 0 | H20: =D20+G20 -> 0
B21: 0400-140 | C21: SAM Advance Co For Industry | D21: 0 | E21: 16145002 | F21: 16146224 | G21: =E21-F21 -> -1222.2 | H21: =D21+G21 -> -1222.2 | I21: Accounts receivable
B22: 0400-138 | C22: United Gulf Factory For Plastics | D22: 0 | E22: 52969 | F22: 52969 | G22: =E22-F22 -> 0 | H22: =D22+G22 -> 0 | I22: Accounts receivable
B23: 0400-137 | C23: Hamed Ateeq Raziq Al-Harbi Environmental Services Est. | D23: 0 | E23: 15719.81 | F23: 15719.85 | G23: =E23-F23 -> -0.04 | H23: =D23+G23 -> -0.04 | I23: Accounts receivable
B24: 0400-02 | C24: AL JAZEERA MODEL PLASTIC FACTORY | D24: 0 | E24: 200701.8 | F24: 167048.05 | G24: =E24-F24 -> 33653.75 | H24: =D24+G24 -> 33653.75 | I24: Accounts receivable
B25: 0605-03 | C25: Saudi Steel Reinforcements Ltd. | D25: 0 | E25: 10399.23 | F25: 10125.4 | G25: =E25-F25 -> 273.83 | H25: =D25+G25 -> 273.83 | I25: Accounts receivable
B26: 0400-10 | C26: MUHAMMAD NASIR SANOSI BAGHDADI PLASTIC FACTORY | D26: 0 | E26: 28230.2 | F26: 25424.3 | G26: =E26-F26 -> 2805.9 | H26: =D26+G26 -> 2805.9 | I26: Accounts receivable
B27: 0400-13 | C27: Rafeeq Bilal Plastic Pvt Ltd | D27: 0 | E27: 67742.45 | F27: 61111 | G27: =E27-F27 -> 6631.45 | H27: =D27+G27 -> 6631.45 | I27: Accounts receivable
B28: 0400-15 | C28: SAPAPCO | D28: 0 | E28: 61331.23 | F28: 51528.28 | G28: =E28-F28 -> 9802.95 | H28: =D28+G28 -> 9802.95 | I28: Accounts receivable
B29: 0400-17 | C29: STAR PLASTIC TRADING COMPANY | D29: 0 | E29: 651340.45 | F29: 486660 | G29: =E29-F29 -> 164680.45 | H29: =D29+G29 -> 164680.45 | I29: Accounts receivable
B30: 0400-20 | C30: Zomorrodah Factory Plastic Industries | D30: 0 | E30: 13878.71 | F30: 13885.93 | G30: =E30-F30 -> -7.22 | H30: =D30+G30 -> -7.22 | I30: Accounts receivable
B31: 0400-25 | C31: Various Customers | D31: 0 | E31: 0 | F31: 6880 | G31: =E31-F31 -> -6880 | H31: =D31+G31 -> -6880 | I31: Accounts receivable
B32: 0400-26 | C32: Shawahid Al-Jazeera Company Ltd | D32: 0 | E32: 24840 | F32: 24840 | G32: =E32-F32 -> 0 | H32: =D32+G32 -> 0 | I32: Accounts receivable
... B81: 0400-146 | C81: MATUWIRIN ALBLASTIC COMPANY | D81: 0 | E81: 99264.55 | F81: 96600 | G81: =E81-F81 -> 2664.55 | H81: =D81+G81 -> 2664.55 | I81: Accounts receivable
B82: 490 | C82: VAT | G82: =E82-F82 -> 0 | H82: =D82+G82 -> 0
B83: VI-001 | C83: Vat Input Account | D83: 0 | E83: 977485.76 | F83: 741334.96 | G83: =E83-F83 -> 236150.8 | H83: =D83+G83 -> 236150.8 | I83: Other current assets
B84: VO-002 | C84: Vat Output Account | D84: 0 | E84: 2893001.9 | F84: 3096628.1 | G84: =E84-F84 -> -203626.26 | H84: =D84+G84 -> -203626.26 | I84: Other current assets
B85: VOA2-003 | C85: Net Vat Refundable / Payable. | D85: -8133.72 | E85: 159260.85 | F85: 148976.09 | G85: =E85-F85 -> 10284.76 | H85: =D85+G85 -> 2151.04 | I85: Other current assets
B86: VOA1-005 | C86: Vat Receiveable | D86: 0 | E86: 235.17 | F86: 0 | G86: =E86-F86 -> 235.17 | H86: =D86+G86 -> 235.17 | I86: Other current assets
B87: VAD-006 | C87: Vat Advance Account | D87: 37956.79 | E87: 1949.29 | F87: 39510.67 | G87: =E87-F87 -> -37561.38 | H87: =D87+G87 -> 395.41 | I87: Other current assets
B88: 601 | C88: Prepaid Expenses | G88: =E88-F88 -> 0 | H88: =D88+G88 -> 0 | I88: Prepayments and other receivables
B89: 0601-01 | C89: Prepaid-Rent Factory | D89: 0 | E89: 93143.05 | F89: 62730 | G89: =E89-F89 -> 30413.05 | H89: =D89+G89 -> 30413.05 | I89: Prepayments and other receivables
B90: 0601-02 | C90: Prepaid-Medical Insurance | D90: 0 | E90: 186025.46 | F90: 77510.55 | G90: =E90-F90 -> 108514.91 | H90: =D90+G90 -> 108514.91 | I90: Prepayments and other receivables
B91: 0601-14 | C91: Prepaid Vehicle Insurance-Wataniya Insurance | D91: 0 | E91: 10843.87 | F91: 3943.2 | G91: =E91-F91 -> 6900.67 | H91: =D91+G91 -> 6900.67 | I91: Prepayments and other receivables
B92: 0601-18 | C92: Prepaid Bupa Medical - Exp | D92: 0 | E92: 46506.33 | F92: 46506.33 | G92: =E92-F92 -> 0 | H92: =D92+G92 -> 0 | I92: Prepayments and other receivables
B93: 0601-20 | C93: Prepaid MWAN License Fee | D93: 0 | E93: 0 | F93: 7492.63 | G93: =E93-F93 -> -7492.63 | H93: =D93+G93 -> -7492.63 | I93: Prepayments and other receivables
B94: 602 | C94: Staff Advances | G94: =E94-F94 -> 0 | H94: =D94+G94 -> 0 | I94: Other current assets
B95: 0602-042 | C95: Ashraf Ghazali ID-233 | D95: 0 | E95: 3200 | F95: 3200 | G95: =E95-F95 -> 0 | H95: =D95+G95 -> 0 | I95: Other current assets
B96: 0602-048 | C96: Ibrahim Ali Al Barkati ID-506 | D96: 0 | E96: 11211 | F96: 11211 | G96: =E96-F96 -> 0 | H96: =D96+G96 -> 0 | I96: Other current assets
B97: 0602-001 | C97: Usman Tanwar | D97: 0 | E97: 156954.54 | F97: 46198.53 | G97: =E97-F97 -> 110756.01 | H97: =D97+G97 -> 110756.01 | I97: Other current assets
B98: 0602-004 | C98: Mohammed Omer Tanwer | D98: 0 | E98: 104098.21 | F98: 0 | G98: =E98-F98 -> 104098.21 | H98: =D98+G98 -> 104098.21 | I98: Other current assets
B99: 0602-046 | C99: Abdul Kalam Patan ID#259 | D99: 0 | E99: 7185 | F99: 7185 | G99: =E99-F99 -> 0 | H99: =D99+G99 -> 0 | I99: Other current assets
B100: 0602-045 | C100: Abdul Alim ID#531 | D100: 0 | E100: 6290 | F100: 6290 | G100: =E100-F100 -> 0 | H100: =D100+G100 -> 0 | I100: Other current assets
B101: 0602-012 | C101: ROSHIDUL ISLAM RAJU ID-493 | D101: 0 | E101: 500 | F101: 500 | G101: =E101-F101 -> 0 | H101: =D101+G101 -> 0 | I101: Other current assets
B102: 0602-014 | C102: MD Mohsin - ID # 479 | D102: 0 | E102: 200 | F102: 200 | G102: =E102-F102 -> 0 | H102: =D102+G102 -> 0 | I102: Other current assets
B103: 0602-016 | C103: Fakhruddin Qasmi - ID # 160 | D103: 0 | E103: 22695 | F103: 30400.53 | G103: =E103-F103 -> -7705.53 | H103: =D103+G103 -> -7705.53 | I103: Other current assets
B104: 0602-035 | C104: Moinuddin Panwar ID# 174 | D104: 0 | E104: 10300 | F104: 900 | G104: =E104-F104 -> 9400 | H104: =D104+G104 -> 9400 | I104: Other current assets
B105: 0602-047 | C105: Rajesh ID 136 | D105: 0 | E105: 8417 | F105: 16291 | G105: =E105-F105 -> -7874 | H105: =D105+G105 -> -7874 | I105: Other current assets
B106: 0602-027 | C106: Hossam Al-Bishri # 222 | D106: 0 | E106: 81540.33 | F106: 0 | G106: =E106-F106 -> 81540.33 | H106: =D106+G106 -> 81540.33 | I106: Other current assets
... B112: 0602-038 | C112: ALTAF SIDDIQUE (ID # 2006) | D112: 0 | E112: 600 | F112: 600 | G112: =E112-F112 -> 0 | H112: =D112+G112 -> 0 | I112: Other current assets
B113: 604 | C113: Supplier Advance | G113: =E113-F113 -> 0 | H113: =D113+G113 -> 0 | I113: Other current assets
B114: 0604-18 | C114: Chess International Trading Company B.V. | D114: 0 | E114: 154069.01 | F114: 203808 | G114: =E114-F114 -> -49738.99 | H114: =D114+G114 -> -49738.99 | I114: Other current assets
B115: 0604-02 | C115: Gulf Packaging System - Advance To Supplier | D115: 0 | E115: 322288.65 | F115: 303651.75 | G115: =E115-F115 -> 18636.9 | H115: =D115+G115 -> 18636.9 | I115: Other current assets
B116: 0604-17 | C116: FAM Recycling Fzco | D116: 0 | E116: 257525 | F116: 257525 | G116: =E116-F116 -> 0 | H116: =D116+G116 -> 0 | I116: Other current assets
B117: 0604-16 | C117: ABSM For Safey Devises | D117: 0 | E117: 2000 | F117: 2000 | G117: =E117-F117 -> 0 | H117: =D117+G117 -> 0 | I117: Other current assets
B118: 0604-08 | C118: Branch Makamin Trading Est - Advance To Supplier | D118: 0 | E118: 21045 | F118: 8625 | G118: =E118-F118 -> 12420 | H118: =D118+G118 -> 12420 | I118: Other current assets
B119: 0604-09 | C119: Saudi Can Co - Advance To Supplier | D119: 0 | E119: 7439.29 | F119: 26762.49 | G119: =E119-F119 -> -19323.2 | H119: =D119+G119 -> -19323.2 | I119: Other current assets
B120: 0604-12 | C120: Pharmaceutical Solution Industry. Ltd | D120: 0 | E120: 650000 | F120: 0 | G120: =E120-F120 -> 650000 | H120: =D120+G120 -> 650000 | I120: Other current assets
B121: 0604-19 | C121: Manar Digital Business Company | D121: 0 | E121: 200 | F121: 0 | G121: =E121-F121 -> 200 | H121: =D121+G121 -> 200 | I121: Other current assets
B122: 0700 | C122: Stocks | G122: =E122-F122 -> 0 | H122: =D122+G122 -> 0
B123: 0700-01 | C123: Raw Matetrail Inventory | D123: 534075.65 | E123: 4648096.5 | F123: 3825897.6 | G123: =E123-F123 -> 822198.94 | H123: =D123+G123 -> 1356274.6 | I123: Inventories
B124: 0700-02 | C124: Finished Goods Inventory | D124: 0 | E124: 11867634 | F124: 12231023 | G124: =E124-F124 -> -363389.2 | H124: =D124+G124 -> -363389.2 | I124: Inventories
B125: 0700-03 | C125: Work In Process | D125: 0 | E125: 3560020.2 | F125: 3560020.2 | G125: =E125-F125 -> 0 | H125: =D125+G125 -> 0 | I125: Inventories
B126: 2000 | C126: FA-Costs | G126: =E126-F126 -> 0 | H126: =D126+G126 -> 0
B127: 2000-01 | C127: Plants & Machinery | D127: 0 | E127: 1177446.7 | F127: 139521.8 | G127: =E127-F127 -> 1037924.9 | H127: =D127+G127 -> 1037924.9 | I127: Property, plant and equipment
B128: 2000-02 | C128: Store Equipments | D128: 0 | E128: 51021.8 | F128: 0 | G128: =E128-F128 -> 51021.8 | H128: =D128+G128 -> 51021.8 | I128: Property, plant and equipment
B129: 2000-03 | C129: Office Equipments | D129: 0 | E129: 5109.13 | F129: 0 | G129: =E129-F129 -> 5109.13 | H129: =D129+G129 -> 5109.13 | I129: Property, plant and equipment
B130: 2000-04 | C130: Vehicles | D130: 0 | E130: 88500 | F130: 0 | G130: =E130-F130 -> 88500 | H130: =D130+G130 -> 88500 | I130: Property, plant and equipment
B131: 2000-08 | C131: Lease Hold Improvements. | D131: 0 | E131: 40000 | F131: 0 | G131: =E131-F131 -> 40000 | H131: =D131+G131 -> 40000 | I131: Property, plant and equipment
B132: 2001 | C132: Acc Depreciation | G132: =E132-F132 -> 0 | H132: =D132+G132 -> 0 | I132: Property, plant and equipment
B133: 2001-02 | C133: Acc Dep-Plant & Machinery | D133: 0 | E133: 0 | F133: 53505.71 | G133: =E133-F133 -> -53505.71 | H133: =D133+G133 -> -53505.71 | I133: Property, plant and equipment
B134: 2001-03 | C134: Acc Dep-Store Equipments | D134: 0 | E134: 0 | F134: 4303.32 | G134: =E134-F134 -> -4303.32 | H134: =D134+G134 -> -4303.32 | I134: Property, plant and equipment
B135: 2001-08 | C135: Acc Dep- Lease Hold Improvment | D135: 0 | E135: 0 | F135: 33359.54 | G135: =E135-F135 -> -33359.54 | H135: =D135+G135 -> -33359.54 | I135: Property, plant and equipment
B136: 2001-04 | C136: Acc Dep-Office Equipments | D136: 0 | E136: 0 | F136: 409.18 | G136: =E136-F136 -> -409.18 | H136: =D136+G136 -> -409.18 | I136: Property, plant and equipment
B137: 2001-05 | C137: Acc Dep-Vehicles | D137: 0 | E137: 0 | F137: 28603.55 | G137: =E137-F137 -> -28603.55 | H137: =D137+G137 -> -28603.55 | I137: Property, plant and equipment
B138: 2001-06 | C138: Acc.Dep-Furniture & Fixtures | D138: 0 | E138: 0 | F138: 2297.83 | G138: =E138-F138 -> -2297.83 | H138: =D138+G138 -> -2297.83 | I138: Property, plant and equipment
B139: 2001-07 | C139: Acc.Dep-Computers | D139: 0 | E139: 0 | F139: 263.93 | G139: =E139-F139 -> -263.93 | H139: =D139+G139 -> -263.93 | I139: Property, plant and equipment
B140: 3200 | C140: Trade Suppliers (Accounts Payable) | G140: =E140-F140 -> 0 | H140: =D140+G140 -> 0 | I140: Property, plant and equipment
B141: 3200-311 | C141: First Saudi Company | D141: 0 | E141: 98652.75 | F141: 97710.9 | G141: =E141-F141 -> 941.85 | H141: =D141+G141 -> 941.85 | I141: Trade and other payables
B142: 3200-007 | C142: Ahmed Mohammed Saleh Baeshen & Co | D142: 0 | E142: 13528.5 | F142: 13650.38 | G142: =E142-F142 -> -121.88 | H142: =D142+G142 -> -121.88 | I142: Trade and other payables
B143: 3200-315 | C143: RAYANCO SAUDI TRDING CO | D143: 0 | E143: 100000 | F143: 0 | G143: =E143-F143 -> 100000 | H143: =D143+G143 -> 100000 | I143: Trade and other payables
B144: 3200-316 | C144: Qimat Al Sayadi Trading Company | D144: 0 | E144: 264098.88 | F144: 0 | G144: =E144-F144 -> 264098.88 | H144: =D144+G144 -> 264098.88 | I144: Trade and other payables
B145: 3200-023 | C145: Fast Arrow Operation & Maintenance | D145: 0 | E145: 0 | F145: 415.5 | G145: =E145-F145 -> -415.5 | H145: =D145+G145 -> -415.5 | I145: Trade and other payables
B146: 3200-038 | C146: Middle East Plastic Industries | D146: 0 | E146: 12038.2 | F146: 12038.2 | G146: =E146-F146 -> 0 | H146: =D146+G146 -> 0 | I146: Trade and other payables
B147: 3200-059 | C147: Nama Advanced Modern Trading Co - Supplier | D147: 0 | E147: 183002.49 | F147: 183002.49 | G147: =E147-F147 -> 0 | H147: =D147+G147 -> 0 | I147: Trade and other payables
B148: 3200-063 | C148: Nasr Packaging & Printing | D148: 0 | E148: 19033.66 | F148: 20165.34 | G148: =E148-F148 -> -1131.68 | H148: =D148+G148 -> -1131.68 | I148: Trade and other payables
B149: 3200-086 | C149: Small Vendors | D149: 0 | E149: 706030 | F149: 706030 | G149: =E149-F149 -> 0 | H149: =D149+G149 -> 0 | I149: Trade and other payables
B150: 3200-095 | C150: Namma Al Enjaz Factory For Industry - Purchase | D150: -534075.65 | E150: 0 | F150: 859664.68 | G150: =E150-F150 -> -859664.68 | H150: =D150+G150 -> -1393740.3 | I150: Short term debt receivable from RP
B151: 3200-111 | C151: Dadco Co | D151: 0 | E151: 3570 | F151: 3570 | G151: =E151-F151 -> 0 | H151: =D151+G151 -> 0 | I151: Trade and other payables
B152: 3200-114 | C152: AL JAZEERA MODEL PLASTIC FACTORY. | D152: 0 | E152: 11950.15 | F152: 11949.9 | G152: =E152-F152 -> 0.25 | H152: =D152+G152 -> 0.25 | I152: Trade and other payables
... B192: 3200-309 | C192: Major Vendor | D192: 0 | E192: 1333101.6 | F192: 1953941.1 | G192: =E192-F192 -> -620839.53 | H192: =D192+G192 -> -620839.53 | I192: Trade and other payables
B193: 3201 | C193: Expenses Payable | G193: =E193-F193 -> 0 | H193: =D193+G193 -> 0
B194: 3201-01 | C194: Accrued Expenses | D194: 0 | E194: 470815.86 | F194: 613097.61 | G194: =E194-F194 -> -142281.75 | H194: =D194+G194 -> -142281.75 | I194: Other liabilities
...

Sheet bs and cf
B1: ='[1]PL-Mgmt'!B1 -> Greencity International
B2: Balance Sheet | H2: Cash Flow Report
D3: In house | E3: In house | J3: In house | K3: In house
B4: Period | D4: 45808 | E4: 46022 | H4: Period | J4: =D4 -> 45808 | K4: =E4 -> 46022
H5: OPERATING ACTIVITIES
B6: Non Current Assets | H6: Net income before zakat and income tax | J6: =D26+D27 -> 255542.42
B7: Property, plant and equipment | D7: =SUMIF(trial!$I$7:$I$359,'bs and cf'!B7,trial!$H$7:$H$360) -> 1099812.7
B8: Capital work in progress | D8: =SUMIF(trial!$I$7:$I$359,'bs and cf'!B8,trial!$H$7:$H$360) -> 0 | E8: 0 | H8: Adjustments for:
B9: Right on use of assets | D9: =SUMIF(trial!$I$7:$I$359,'bs and cf'!B9,trial!$H$7:$H$360) -> 0 | E9: 0 | H9: Depreciation and amortization | J9: 0
B10: Intangible assets | D10: =SUMIF(trial!$I$7:$I$359,'bs and cf'!B10,trial!$H$7:$H$360) -> 0 | H10: Finance charges | J10: 0
B11: Total Non Current Assets | D11: =SUM(D7:D10) -> 1099812.7 | E11: =SUM(E7:E10) -> 0 | H11: (Gain)/Loss from sale of property and equipment | J11: 0
H12: Allowance for Obsolete & slow moving inventory | J12: 0
B13: Current Assets | H13: Employees’ end of service benefits | J13: =SUM(D33-E33) -> 359740.9
B14: Inventories | D14: =SUMIF(trial!$I$7:$I$359,'bs and cf'!B14,trial!$H$7:$H$360) -> 992885.39
B15: Accounts receivable | D15: =SUMIF(trial!$I$7:$I$359,'bs and cf'!B15,trial!$H$7:$H$360) -> 1024656.5 | H15: Changes in operating assets and liabilities:
B16: Prepayments and other receivables | D16: =SUMIF(trial!$I$7:$I$359,'bs and cf'!B16,trial!$H$7:$H$360) -> 138336 | H16: Inventories | J16: =E14-D14 -> -992885.39
B17: Other current assets | D17: =SUMIF(trial!$I$7:$I$359,'bs and cf'!B17,trial!$H$7:$H$360) -> 986606.75 | H17: Trade receivables | J17: =E15-D15 -> -1024656.5
B18: Short term debt receivable from RP | D18: =SUMIF(trial!$I$7:$I$359,'bs and cf'!B18,trial!$H$7:$H$360) -> 668205.82 | H18: Prepayments and other receivables | J18: =E16-D16 -> -138336
B19: Bank balances and cash | D19: =SUMIF(trial!$I$7:$I$359,'bs and cf'!B19,trial!$H$7:$H$360) -> 53747.59 | H19: Other current assets | J19: =E17-D17 -> -986606.75
B20: Total Current Assets | D20: =SUM(D14:D19) -> 3864438.1 | E20: =SUM(E14:E19) -> 0 | H20: Trade and other payables | J20: =SUM(D41-E41) -> 3545230.8
B21: TOTAL ASSETS | D21: =D20+D11 -> 4964250.8 | E21: =E20+E11 -> 0 | H21: Other current liabilities | J21: =D42-E42 -> 668647.96
H22: Cash from operations | J22: =SUM(J6:J21) -> 1686677.4 | K22: =SUM(K6:K21) -> 0
B23: Equity | H23: Finance cost paid | J23: 0 | K23: 0
B24: Owner Contribution | D24: =-SUMIF(trial!$I$7:$I$359,'bs and cf'!B24,trial!$H$7:$H$360) -> 135088.69 | E24: 0 | H24: Zakat paid | J24: 0 | K24: 0
B25: Statutory Reserves | D25: =-SUMIF(trial!$I$7:$I$359,'bs and cf'!B25,trial!$H$7:$H$360) -> 0 | E25: 0 | H25: Employees’ end of service benefit paid | J25: 0 | K25: 0
B26: Current Year Profit (Loss) | D26: =-SUMIF(trial!$I$7:$I$359,'bs and cf'!B26,trial!$H$7:$H$360) -> 316920.94 | E26: 0 | H26: Net cash from operating activities | J26: =SUM(J22:J25) -> 1686677.4 | K26: =SUM(K22:K25) -> 0
B27: Retained Earnings | D27: =-SUMIF(trial!$I$7:$I$359,'bs and cf'!B27,trial!$H$7:$H$360) -> -61378.52
B28: Total equity | D28: =SUM(D24:D27) -> 390631.11 | E28: =SUM(E24:E27) -> 0 | H28: INVESTING ACTIVITIES
H29: Acquisition of property and equipment and intangible assets | J29: =E11-D11 -> -1099812.7
B30: Non-current liability | H30: Owner Contribution | J30: =SUM(D24-E24) -> 135088.69 | K30: 0
B31: Long-term loans | D31: =-SUMIF(trial!$I$7:$I$359,'bs and cf'!B31,trial!$H$7:$H$360) -> 0 | E31: 0 | H31: Proceeds from disposal of PPE | J31: 0 | K31: 0
B32: Long-term lease liability | D32: =-SUMIF(trial!$I$7:$I$359,'bs and cf'!B32,trial!$H$7:$H$360) -> 0 | E32: 0 | H32: Other Financial Liability | K32: 0
B33: Employees' end of service benefits | D33: =-SUMIF(trial!$I$7:$I$359,'bs and cf'!B33,trial!$H$7:$H$360) -> 359740.9 | H33: Short term loan | J33: =E18-D18 -> -668205.82
B34: Total Non Current liabilities | D34: =SUM(D31:D33) -> 359740.9 | E34: =SUM(E31:E33) -> 0 | H34: Net cash from investing activities | J34: =SUM(J29:J33) -> -1632929.9 | K34: =SUM(K29:K33) -> 0
B36: Current liabilities | H36: FINANCING ACTIVITIES
B37: Zakat Payable | D37: =-SUMIF(trial!$I$7:$I$359,'bs and cf'!B37,trial!$H$7:$H$360) -> 0 | E37: 0 | H37: Net cash in short term borrowings | J37: =D40-E40 -> 0
B38: Current portion of long-term debt | D38: =-SUMIF(trial!$I$7:$I$359,'bs and cf'!B38,trial!$H$7:$H$360) -> 0 | E38: 0 | H38: Proceeds from long term borrowings | J38: 0
B39: Current portion of lease liability | D39: =-SUMIF(trial!$I$7:$I$359,'bs and cf'!B39,trial!$H$7:$H$360) -> 0 | E39: 0 | H39: Repayments of long term borrowings | J39: 0 | K39: 0
B40: Short-term borrowings | D40: =-SUMIF(trial!$I$7:$I$359,'bs and cf'!B40,trial!$H$7:$H$360) -> 0 | H40: Principal Payments of lease liability | J40: 0 | K40: 0
B41: Trade and other payables | D41: =-SUMIF(trial!$I$7:$I$359,'bs and cf'!B41,trial!$H$7:$H$360) -> 3545230.8 | H41: Principal Payments of other financial liability | J41: 0 | K41: 0
B42: Other liabilities | D42: =-SUMIF(trial!$I$7:$I$359,'bs and cf'!B42,trial!$H$7:$H$360) -> 668647.96 | H42: Net cash (used in)/from financing activities | J42: =SUM(J37:J41) -> 0 | K42: =SUM(K37:K41) -> 0
B43: Total Current liabilities | D43: =SUM(D37:D42) -> 4213878.8 | E43: =SUM(E37:E42) -> 0
B44: Total Liabilities | D44: =(D43+D34) -> 4573619.7 | E44: =(E43+E34) -> 0 | H44: Net change in cash and cash equivalents | J44: =J42+J34+J26 -> 53747.57 | K44: =K42+K34+K26 -> 0
B45: TOTAL EQUITY AND LIABILITIES | D45: =(D44+D28) -> 4964250.8 | E45: =(E44+E28) -> 0 | H45: Cash and cash equivalents, January 1 | J45: =E19 -> 0 | K45: 0
D46: =D21-D45 -> 0.020000004 | E46: =E21-E45 -> 0 | H46: Closing Cash and Bank | J46: =J45+J44 -> 53747.57 | K46: =K45+K44 -> 0
J47: =J46-D19 -> -0.020000005
D48: 0
D49: 0
D50: 0 | E50: =D48+D49-D50 -> 0
